mistymountain/__init__.py
mistymountain/__main__.py
mistymountain/version.py
mistymountain-0.1.0.dev0.dist-info/METADATA
mistymountain-0.1.0.dev0.dist-info/WHEEL
mistymountain-0.1.0.dev0.dist-info/top_level.txt
mistymountain-0.1.0.dev0.dist-info/RECORD
