Metadata-Version: 2.1
Name: mistymountain
Version: 0.1.0.dev0
Summary: Cloud Based Helper Library
